<?xml version="1.0" encoding="utf-8"?>
<openerp>
    <data>

        <template id="subsribe_thanks" name="Subsribe Thanks">
            <t t-call="website.layout">
                <div id="wrap" class="oe_structure oe_empty">
                    <div class="container">
                        <div class="row">
                            <h1 class="text-center">Thanks</h1>
                        </div>
                    </div>
                </div>
            </t>
        </template>

    </data>
</openerp>
